thconfig/__init__.py
thconfig/config.py
thconfig/error.py
thconfig/file/__init__.py
thconfig/file/file_config.py
thconfig/http/__init__.py
thconfig/http/couch_config.py
thconfig/http/etcd_config.py
thconfig/http/http_config.py
thconfig-0.9.8.dist-info/LICENSE
thconfig-0.9.8.dist-info/METADATA
thconfig-0.9.8.dist-info/WHEEL
thconfig-0.9.8.dist-info/RECORD
