Metadata-Version: 2.1
Name: thconfig
Version: 0.9.8
Summary: TangledHub Config reader/writter
Home-page: https://gitlab.com/tangledlabs/thconfig
License: BSD 3-clause
Keywords: tangled,tangledhub,tangledlabs,thconfig
Author: TangledHub
Author-email: info@tangledgroup.com
Requires-Python: >=3.10,<4.0
Classifier: Development Status :: 4 - Beta
Classifier: Intended Audience :: Developers
Classifier: License :: OSI Approved :: BSD License
Classifier: License :: Other/Proprietary License
Classifier: Operating System :: OS Independent
Classifier: Programming Language :: Python
Classifier: Programming Language :: Python :: 3
Classifier: Programming Language :: Python :: 3.10
Classifier: Programming Language :: Python :: 3.11
Classifier: Programming Language :: Python :: 3.10
Classifier: Programming Language :: Python :: 3.11
Classifier: Topic :: Software Development :: Libraries :: Python Modules
Provides-Extra: aetcd
Requires-Dist: PyYAML (>=6.0,<7.0)
Requires-Dist: aiohttp (>=3.8.3,<4.0.0)
Requires-Dist: json5 (>=0.9.10,<0.10.0)
Requires-Dist: thresult (>=0.9.25,<0.10.0)
Requires-Dist: toml (>=0.10.2,<0.11.0)
Project-URL: Repository, https://gitlab.com/tangledlabs/thconfig
